carepoint/__init__.py
carepoint/db/__init__.py
carepoint/db/carepoint.py
carepoint/db/db.py
carepoint/models/__init__.py
carepoint/models/address_mixin.py
carepoint/models/phone_mixin.py
carepoint/models/state.py
carepoint/models/cph/__init__.py
carepoint/models/cph/account.py
carepoint/models/cph/account_activity.py
carepoint/models/cph/address.py
carepoint/models/cph/dispense.py
carepoint/models/cph/dispense_price.py
carepoint/models/cph/doctor.py
carepoint/models/cph/doctor_address.py
carepoint/models/cph/doctor_phone.py
carepoint/models/cph/fdb_allergen.py
carepoint/models/cph/fdb_allergen_desc.py
carepoint/models/cph/fdb_allergen_group.py
carepoint/models/cph/fdb_allergen_rel.py
carepoint/models/cph/fdb_attr.py
carepoint/models/cph/fdb_attr_base.py
carepoint/models/cph/fdb_attr_type.py
carepoint/models/cph/fdb_form.py
carepoint/models/cph/fdb_gcn.py
carepoint/models/cph/fdb_gcn_seq.py
carepoint/models/cph/fdb_img.py
carepoint/models/cph/fdb_img_date.py
carepoint/models/cph/fdb_img_id.py
carepoint/models/cph/fdb_img_mfg.py
carepoint/models/cph/fdb_lbl_rid.py
carepoint/models/cph/fdb_ndc.py
carepoint/models/cph/fdb_ndc_cs_ext.py
carepoint/models/cph/fdb_pem_moe.py
carepoint/models/cph/fdb_pem_mogc.py
carepoint/models/cph/fdb_price.py
carepoint/models/cph/fdb_price_type.py
carepoint/models/cph/fdb_route.py
carepoint/models/cph/fdb_unit.py
carepoint/models/cph/image_data.py
carepoint/models/cph/item.py
carepoint/models/cph/order.py
carepoint/models/cph/order_line.py
carepoint/models/cph/order_line_non_rx.py
carepoint/models/cph/order_ship.py
carepoint/models/cph/order_status.py
carepoint/models/cph/organization.py
carepoint/models/cph/organization_address.py
carepoint/models/cph/pathology.py
carepoint/models/cph/pathology_code_type.py
carepoint/models/cph/patient.py
carepoint/models/cph/patient_address.py
carepoint/models/cph/patient_allergy.py
carepoint/models/cph/patient_disease.py
carepoint-0.1.8b665.dist-info/DESCRIPTION.rst
carepoint-0.1.8b665.dist-info/METADATA
carepoint-0.1.8b665.dist-info/RECORD
carepoint-0.1.8b665.dist-info/WHEEL
carepoint-0.1.8b665.dist-info/metadata.json
carepoint-0.1.8b665.dist-info/top_level.txt
