Metadata-Version: 2.0
Name: carepoint
Version: 0.1.8b665
Summary: This library will allow you to interact with a remote CarePoint instance using Python.
Home-page: https://laslabs.github.io/python-carepoint
Author: LasLabs Inc.
Author-email: support@laslabs.com
License: MIT
Download-URL: https://github.com/LasLabs/python-carepoint
Platform: UNKNOWN
Classifier: Development Status :: 4 - Beta
Classifier: Environment :: Console
Classifier: Intended Audience :: Developers
Classifier: Intended Audience :: Healthcare Industry
Classifier: License :: OSI Approved :: MIT License
Classifier: Operating System :: POSIX :: Linux
Classifier: Programming Language :: Python
Classifier: Topic :: Software Development :: Libraries :: Python Modules
Requires-Dist: SQLAlchemy (>=1.1.1)
Requires-Dist: enum34 (>=1.1.6)
Requires-Dist: pyodbc (>=3.0.10)
Requires-Dist: pysmb (>=1.1.18)
